django_geohash_cluster-0.1.0.dist-info/DESCRIPTION.rst
django_geohash_cluster-0.1.0.dist-info/METADATA
django_geohash_cluster-0.1.0.dist-info/RECORD
django_geohash_cluster-0.1.0.dist-info/WHEEL
django_geohash_cluster-0.1.0.dist-info/metadata.json
django_geohash_cluster-0.1.0.dist-info/top_level.txt
geohash_cluster/__init__.py
geohash_cluster/apps.py
geohash_cluster/models.py
geohash_cluster/rest_framework.py
