Metadata-Version: 2.0
Name: django-geohash-cluster
Version: 0.1.0
Summary: High efficient clustering algorithm based on geohash of points
Home-page: https://github.com/EvgeneOskin/django-geohash-cluster
Author: Your full name here
Author-email: Eugene Oskin: eoskin@crystalnix.com
License: MIT
Keywords: django-geohash-cluster
Platform: UNKNOWN
Classifier: Development Status :: 3 - Alpha
Classifier: Framework :: Django
Classifier: Framework :: Django :: 1.8
Classifier: Framework :: Django :: 1.9
Classifier: Framework :: Django :: 1.10
Classifier: Intended Audience :: Developers
Classifier: License :: OSI Approved :: BSD License
Classifier: Natural Language :: English
Classifier: Programming Language :: Python :: 2
Classifier: Programming Language :: Python :: 2.7
Classifier: Programming Language :: Python :: 3
Classifier: Programming Language :: Python :: 3.3
Classifier: Programming Language :: Python :: 3.4
Classifier: Programming Language :: Python :: 3.5
Requires-Dist: django (>=1.8)
Provides-Extra: rest
Requires-Dist: django-filter; extra == 'rest'
Requires-Dist: django-rest-framework; extra == 'rest'
Requires-Dist: djangorestframework-gis; extra == 'rest'
Requires-Dist: python-geohash; extra == 'rest'
